ahb2apb_bridge.srcs/sources_1/new/apb_controller.v
module apb_controller (
    input         HCLK, HRESETn,
    input  [31:0] slv_addr, slv_wdata,
    input         slv_write, slv_valid,
    output reg        PSEL, PENABLE, PWRITE, PRESETn,
    output reg [31:0] PADDR, PWDATA,
    input      [31:0] PRDATA,
    input             PREADY,
    output reg        apb_done
);
    localparam IDLE=2'b00, SETUP=2'b01, ACCESS=2'b10;
    reg [1:0] state, next_state;

    always @(posedge HCLK or negedge HRESETn)
        if (!HRESETn) state <= IDLE;
        else          state <= next_state;

    always @(posedge HCLK or negedge HRESETn)
        if (!HRESETn) PRESETn <= 0;
        else          PRESETn <= 1;

    always @(*) begin
        next_state=IDLE; PSEL=0; PENABLE=0;
        PWRITE=0; PADDR=0; PWDATA=0; apb_done=0;
        case (state)
            IDLE:   if (slv_valid) next_state = SETUP;

            SETUP: begin
                PSEL=1; PENABLE=0;
                PWRITE=slv_write; PADDR=slv_addr; PWDATA=slv_wdata;
                next_state = ACCESS;
            end

            ACCESS: begin
                PSEL=1; PENABLE=1;
                PWRITE=slv_write; PADDR=slv_addr; PWDATA=slv_wdata;
                if (PREADY) begin apb_done=1; next_state=IDLE; end
                else        begin apb_done=0; next_state=ACCESS; end
            end
        endcase
    end
endmodule

ahb2apb_bridge.srcs/sources_1/new/ahb_slave_interface.v
module ahb_slave_interface (
    input         HCLK, HRESETn,
    input         HSEL,
    input  [1:0]  HTRANS,
    input         HWRITE, HREADY,
    input  [31:0] HADDR, HWDATA,
    output reg [31:0] slv_addr, slv_wdata,
    output reg        slv_write, slv_valid,
    input             apb_done,
    output            HREADYOUT,
    input      [31:0] PRDATA,
    output     [31:0] HRDATA
);
    wire valid_ahb = HSEL & HREADY & HTRANS[1];

    always @(posedge HCLK or negedge HRESETn) begin
        if (!HRESETn) begin
            slv_addr  <= 0; slv_wdata <= 0;
            slv_write <= 0; slv_valid <= 0;
        end else begin
            slv_valid <= valid_ahb;
            if (valid_ahb) begin
                slv_addr  <= HADDR;
                slv_write <= HWRITE;
            end
            if (slv_valid)
                slv_wdata <= HWDATA;
        end
    end

    assign HREADYOUT = apb_done | ~slv_valid;
    assign HRDATA    = PRDATA;
endmodule

ahb2apb_bridge.srcs/sources_1/new/ahb2apb_bridge.v
module ahb2apb_bridge (
    input         HCLK, HRESETn,
    input         HSEL, HWRITE, HREADY,
    input  [1:0]  HTRANS,
    input  [31:0] HADDR, HWDATA,
    output        HREADYOUT,
    output [31:0] HRDATA,
    output        PSEL, PENABLE, PWRITE, PRESETn,
    output [31:0] PADDR, PWDATA,
    input  [31:0] PRDATA,
    input         PREADY
);
    wire [31:0] slv_addr, slv_wdata;
    wire        slv_write, slv_valid, apb_done;

    ahb_slave_interface u0 (
        .HCLK(HCLK),         .HRESETn(HRESETn),
        .HSEL(HSEL),          .HTRANS(HTRANS),
        .HWRITE(HWRITE),      .HREADY(HREADY),
        .HADDR(HADDR),        .HWDATA(HWDATA),
        .slv_addr(slv_addr),  .slv_wdata(slv_wdata),
        .slv_write(slv_write),.slv_valid(slv_valid),
        .apb_done(apb_done),
        .HREADYOUT(HREADYOUT),
        .PRDATA(PRDATA),      .HRDATA(HRDATA)
    );

    apb_controller u1 (
        .HCLK(HCLK),           .HRESETn(HRESETn),
        .slv_addr(slv_addr),   .slv_wdata(slv_wdata),
        .slv_write(slv_write), .slv_valid(slv_valid),
        .PSEL(PSEL),            .PENABLE(PENABLE),
        .PWRITE(PWRITE),        .PRESETn(PRESETn),
        .PADDR(PADDR),          .PWDATA(PWDATA),
        .PRDATA(PRDATA),        .PREADY(PREADY),
        .apb_done(apb_done)
    );
endmodule

ahb2apb_bridge.srcs/sim_1/new/tb_ahb2apb.v
`timescale 1ns/1ps
module tb_ahb2apb;

    reg         HCLK, HRESETn, HSEL, HWRITE, HREADY;
    reg  [1:0]  HTRANS;
    reg  [31:0] HADDR, HWDATA, PRDATA;
    reg         PREADY;
    wire        HREADYOUT;
    wire [31:0] HRDATA, PADDR, PWDATA;
    wire        PSEL, PENABLE, PWRITE, PRESETn;

    ahb2apb_bridge dut (
        .HCLK(HCLK),          .HRESETn(HRESETn),
        .HSEL(HSEL),           .HWRITE(HWRITE),
        .HREADY(HREADY),       .HTRANS(HTRANS),
        .HADDR(HADDR),         .HWDATA(HWDATA),
        .HREADYOUT(HREADYOUT), .HRDATA(HRDATA),
        .PSEL(PSEL),           .PENABLE(PENABLE),
        .PWRITE(PWRITE),       .PRESETn(PRESETn),
        .PADDR(PADDR),         .PWDATA(PWDATA),
        .PRDATA(PRDATA),       .PREADY(PREADY)
    );

    // Clock
    initial HCLK = 0;
    always #5 HCLK = ~HCLK;

    // Write Task
    task ahb_write;
        input [31:0] addr;
        input [31:0] data;
        begin
            @(posedge HCLK);
            HSEL=1; HWRITE=1; HREADY=1;
            HTRANS=2'b10; HADDR=addr; HWDATA=data;
            @(posedge HCLK);
            HSEL=0; HTRANS=2'b00;
            PREADY=1;
            #20;
            PREADY=0;
            $display("WRITE: ADDR=%h DATA=%h PADDR=%h PWDATA=%h",
                      addr, data, PADDR, PWDATA);
        end
    endtask

    // Read Task
    task ahb_read;
        input [31:0] addr;
        input [31:0] rdata;
        begin
            @(posedge HCLK);
            HSEL=1; HWRITE=0; HREADY=1;
            HTRANS=2'b10; HADDR=addr; PRDATA=rdata;
            @(posedge HCLK);
            HSEL=0; HTRANS=2'b00;
            PREADY=1;
            #20;
            PREADY=0;
            $display("READ: ADDR=%h HRDATA=%h",
                      addr, HRDATA);
        end
    endtask

    // Main Test
    initial begin
        $dumpfile("ahb2apb.vcd");
        $dumpvars(0, tb_ahb2apb);

        // Reset
        HRESETn=0; HSEL=0; HWRITE=0;
        HREADY=1; HTRANS=0; HADDR=0;
        HWDATA=0; PRDATA=0; PREADY=0;
        repeat(4) @(posedge HCLK);
        HRESETn=1;
        repeat(2) @(posedge HCLK);

        // Test 1: Write
        ahb_write(32'h4000_0000, 32'hDEAD_BEEF);
        repeat(2) @(posedge HCLK);

        // Test 2: Write
        ahb_write(32'h4000_0004, 32'hCAFE_BABE);
        repeat(2) @(posedge HCLK);

        // Test 3: Read
        ahb_read(32'h4000_0000, 32'h1234_5678);
        repeat(2) @(posedge HCLK);

        repeat(5) @(posedge HCLK);
        $display("=== Simulation Done ===");
        $finish;
    end

endmodule

ahb2apb_bridge.sim/sim_1/behav/xsim/ahb2apb.vcd
$date
   Tue Jun 16 10:40:52 2026
$end

$version
  2024.2.0
  $dumpfile ("ahb2apb.vcd") 
$end

$timescale
  1ps
$end

$scope module tb_ahb2apb $end
$var reg 1 ! HCLK $end
$var reg 1 " HRESETn $end
$var reg 1 # HSEL $end
$var reg 1 $ HWRITE $end
$var reg 1 % HREADY $end
$var reg 2 & HTRANS [1:0] $end
$var reg 32 ' HADDR [31:0] $end
$var reg 32 ( HWDATA [31:0] $end
$var reg 32 ) PRDATA [31:0] $end
$var reg 1 * PREADY $end
$var wire 1 + HREADYOUT $end
$var wire 32 , HRDATA [31:0] $end
$var wire 32 - PADDR [31:0] $end
$var wire 32 . PWDATA [31:0] $end
$var wire 1 / PSEL $end
$var wire 1 0 PENABLE $end
$var wire 1 1 PWRITE $end
$var wire 1 2 PRESETn $end
$scope module dut $end
$var wire 1 3 HCLK $end
$var wire 1 4 HRESETn $end
$var wire 1 5 HSEL $end
$var wire 1 6 HWRITE $end
$var wire 1 7 HREADY $end
$var wire 2 8 HTRANS [1:0] $end
$var wire 32 9 HADDR [31:0] $end
$var wire 32 : HWDATA [31:0] $end
$var wire 1 + HREADYOUT $end
$var wire 32 , HRDATA [31:0] $end
$var wire 1 / PSEL $end
$var wire 1 0 PENABLE $end
$var wire 1 1 PWRITE $end
$var wire 1 2 PRESETn $end
$var wire 32 - PADDR [31:0] $end
$var wire 32 . PWDATA [31:0] $end
$var wire 32 ; PRDATA [31:0] $end
$var wire 1 < PREADY $end
$var wire 32 = slv_addr [31:0] $end
$var wire 32 > slv_wdata [31:0] $end
$var wire 1 ? slv_write $end
$var wire 1 @ slv_valid $end
$var wire 1 A apb_done $end
$scope module u0 $end
$var wire 1 3 HCLK $end
$var wire 1 4 HRESETn $end
$var wire 1 5 HSEL $end
$var wire 2 8 HTRANS [1:0] $end
$var wire 1 6 HWRITE $end
$var wire 1 7 HREADY $end
$var wire 32 9 HADDR [31:0] $end
$var wire 32 : HWDATA [31:0] $end
$var reg 32 B slv_addr [31:0] $end
$var reg 32 C slv_wdata [31:0] $end
$var reg 1 D slv_write $end
$var reg 1 E slv_valid $end
$var wire 1 A apb_done $end
$var wire 1 + HREADYOUT $end
$var wire 32 ; PRDATA [31:0] $end
$var wire 32 , HRDATA [31:0] $end
$var wire 1 F valid_ahb $end
$upscope $end
$scope module u1 $end
$var wire 1 3 HCLK $end
$var wire 1 4 HRESETn $end
$var wire 32 = slv_addr [31:0] $end
$var wire 32 > slv_wdata [31:0] $end
$var wire 1 ? slv_write $end
$var wire 1 @ slv_valid $end
$var reg 1 G PSEL $end
$var reg 1 H PENABLE $end
$var reg 1 I PWRITE $end
$var reg 1 J PRESETn $end
$var reg 32 K PADDR [31:0] $end
$var reg 32 L PWDATA [31:0] $end
$var wire 32 ; PRDATA [31:0] $end
$var wire 1 < PREADY $end
$var reg 1 M apb_done $end
$var reg 2 N state [1:0] $end
$var reg 2 O next_state [1:0] $end
$upscope $end
$upscope $end
$scope task ahb_write $end
$var reg 32 P addr [31:0] $end
$var reg 32 Q data [31:0] $end
$upscope $end
$scope task ahb_read $end
$var reg 32 R addr [31:0] $end
$var reg 32 S rdata [31:0] $end
$upscope $end
$upscope $end
$enddefinitions $end

#0
$dumpvars
0!
0"
0#
0$
1%
b0 &
b0 '
b0 (
b0 )
0*
1+
b0 ,
b0 -
b0 .
0/
00
01
02
03
04
05
06
17
b0 8
b0 9
b0 :
b0 ;
0<
b0 =
b0 >
0?
0@
0A
b0 B
b0 C
0D
0E
0F
0G
0H
0I
0J
b0 K
b0 L
0M
b0 N
b0 O
bx P
bx Q
bx R
bx S
$end

#5000
1!
13

#10000
0!
03

#15000
1!
13

#20000
0!
03

#25000
1!
13

#30000
0!
03

#35000
1!
1"
12
13
14
1J

#40000
0!
03

#45000
1!
13

#50000
0!
03

#55000
1!
13
b1000000000000000000000000000000 P
b11011110101011011011111011101111 Q

#60000
0!
03

#65000
1!
1#
1$
b10 &
b1000000000000000000000000000000 '
b11011110101011011011111011101111 (
13
15
16
b10 8
b1000000000000000000000000000000 9
b11011110101011011011111011101111 :
1F

#70000
0!
03

#75000
1!
0#
b0 &
1*
0+
13
05
b0 8
1<
b1000000000000000000000000000000 =
1?
1@
b1000000000000000000000000000000 B
1D
1E
0F
b1 O

#80000
0!
03

#85000
1!
1+
b1000000000000000000000000000000 -
b11011110101011011011111011101111 .
1/
11
13
b11011110101011011011111011101111 >
0@
b11011110101011011011111011101111 C
0E
1G
1I
b1000000000000000000000000000000 K
b11011110101011011011111011101111 L
b1 N
b10 O

#90000
0!
03

#95000
1!
0*
10
13
0<
1G
1H
1I
b1000000000000000000000000000000 K
b11011110101011011011111011101111 L
b10 N
b10 O

#100000
0!
03

#105000
1!
13
b1000000000000000000000000000100 P
b11001010111111101011101010111110 Q

#110000
0!
03

#115000
1!
1#
b10 &
b1000000000000000000000000000100 '
b11001010111111101011101010111110 (
13
15
b10 8
b1000000000000000000000000000100 9
b11001010111111101011101010111110 :
1F

#120000
0!
03

#125000
1!
0#
b0 &
1*
b1000000000000000000000000000100 -
13
05
b0 8
1<
b1000000000000000000000000000100 =
1@
1A
b1000000000000000000000000000100 B
1E
0F
1G
1H
1I
b1000000000000000000000000000100 K
b11011110101011011011111011101111 L
1M
b0 O

#130000
0!
03

#135000
1!
b0 -
b0 .
0/
00
01
13
b11001010111111101011101010111110 >
0@
0A
b11001010111111101011101010111110 C
0E
0G
0H
0I
b0 K
b0 L
0M
b0 N

#140000
0!
03

#145000
1!
0*
13
0<

#150000
0!
03

#155000
1!
13
b1000000000000000000000000000000 R
b10010001101000101011001111000 S

#160000
0!
03

#165000
1!
1#
0$
b10 &
b1000000000000000000000000000000 '
b10010001101000101011001111000 )
b10010001101000101011001111000 ,
13
15
06
b10 8
b1000000000000000000000000000000 9
b10010001101000101011001111000 ;
1F

#170000
0!
03

#175000
1!
0#
b0 &
1*
0+
13
05
b0 8
1<
b1000000000000000000000000000000 =
0?
1@
b1000000000000000000000000000000 B
0D
1E
0F
b1 O

#180000
0!
03

#185000
1!
1+
b1000000000000000000000000000000 -
b11001010111111101011101010111110 .
1/
13
0@
0E
1G
b1000000000000000000000000000000 K
b11001010111111101011101010111110 L
b1 N
b10 O

#190000
0!
03

#195000
1!
0*
10
13
0<
1G
1H
b1000000000000000000000000000000 K
b11001010111111101011101010111110 L
b10 N
b10 O

